{
    "key": "group_5eea8c958f5ea",
    "title": "Block &mdash; Columns",
    "fields": [
        {
            "key": "field_5eea92e83af05",
            "label": "General Options",
            "name": "general_options",
            "type": "clone",
            "instructions": "",
            "required": 0,
            "conditional_logic": 0,
            "wrapper": {
                "width": "",
                "class": "",
                "id": ""
            },
            "clone": [
                "group_5eea91f766fa7"
            ],
            "display": "seamless",
            "layout": "block",
            "prefix_label": 0,
            "prefix_name": 0
        },
        {
            "key": "field_5eeaa35314ba7",
            "label": "CTA",
            "name": "cta",
            "type": "clone",
            "instructions": "",
            "required": 0,
            "conditional_logic": 0,
            "wrapper": {
                "width": "",
                "class": "",
                "id": ""
            },
            "clone": [
                "group_5eea90d641e50"
            ],
            "display": "seamless",
            "layout": "block",
            "prefix_label": 0,
            "prefix_name": 0
        },
        {
            "key": "field_5eea8e791027d",
            "label": "Row of Columns",
            "name": "row_of_columns",
            "type": "repeater",
            "instructions": "",
            "required": 0,
            "conditional_logic": 0,
            "wrapper": {
                "width": "",
                "class": "",
                "id": ""
            },
            "collapsed": "",
            "min": 0,
            "max": 0,
            "layout": "row",
            "button_label": "Add Row of Columns",
            "sub_fields": [
                {
                    "key": "field_5eea93453af06",
                    "label": "Column",
                    "name": "column",
                    "type": "repeater",
                    "instructions": "",
                    "required": 0,
                    "conditional_logic": 0,
                    "wrapper": {
                        "width": "",
                        "class": "",
                        "id": ""
                    },
                    "collapsed": "",
                    "min": 2,
                    "max": 5,
                    "layout": "block",
                    "button_label": "Add Column (minimum 2, maximum 5)",
                    "sub_fields": [
                        {
                            "key": "field_5eea93ac3af07",
                            "label": "Column Type",
                            "name": "column_type",
                            "type": "select",
                            "instructions": "",
                            "required": 0,
                            "conditional_logic": 0,
                            "wrapper": {
                                "width": "",
                                "class": "",
                                "id": ""
                            },
                            "choices": {
                                "text": "Text",
                                "image": "Image"
                            },
                            "default_value": "text",
                            "allow_null": 0,
                            "multiple": 0,
                            "ui": 0,
                            "return_format": "value",
                            "ajax": 0,
                            "placeholder": ""
                        },
                        {
                            "key": "field_5ef5185d08daf",
                            "label": "Text Alignment",
                            "name": "text_alignment",
                            "type": "select",
                            "instructions": "",
                            "required": 0,
                            "conditional_logic": [
                                [
                                    {
                                        "field": "field_5eea93ac3af07",
                                        "operator": "==",
                                        "value": "text"
                                    }
                                ]
                            ],
                            "wrapper": {
                                "width": "",
                                "class": "",
                                "id": ""
                            },
                            "choices": {
                                "left": "Left",
                                "center": "Center",
                                "truecenter": "Center Horizontally AND Vertically"
                            },
                            "default_value": "left",
                            "allow_null": 0,
                            "multiple": 0,
                            "ui": 0,
                            "return_format": "value",
                            "ajax": 0,
                            "placeholder": ""
                        },
                        {
                            "key": "field_5f07616a124c2",
                            "label": "Background Color",
                            "name": "background_color",
                            "type": "select",
                            "instructions": "",
                            "required": 0,
                            "conditional_logic": [
                                [
                                    {
                                        "field": "field_5eea93ac3af07",
                                        "operator": "==",
                                        "value": "text"
                                    }
                                ]
                            ],
                            "wrapper": {
                                "width": "",
                                "class": "",
                                "id": ""
                            },
                            "choices": {
                                "#FFFFFF": "White (Default)",
                                "#C20DD1": "Magenta",
                                "#7311F2": "Purple",
                                "#3AD0F9": "Cyan",
                                "#F86864": "Orange",
                                "#000F8C": "Deep Blue",
                                "#0C3675": "Slate",
                                "#000255": "Dark Blue",
                                "#A0A6CA": "Gray",
                                "#DFE2F0": "Medium Gray (dark text)",
                                "#F5F5F6": "Light Gray (dark text)"
                            },
                            "default_value": "#FFFFFF",
                            "allow_null": 1,
                            "multiple": 0,
                            "ui": 0,
                            "return_format": "value",
                            "ajax": 0,
                            "placeholder": ""
                        },
                        {
                            "key": "field_5eea93d83af08",
                            "label": "Text",
                            "name": "text",
                            "type": "wysiwyg",
                            "instructions": "",
                            "required": 0,
                            "conditional_logic": [
                                [
                                    {
                                        "field": "field_5eea93ac3af07",
                                        "operator": "==",
                                        "value": "text"
                                    }
                                ]
                            ],
                            "wrapper": {
                                "width": "",
                                "class": "",
                                "id": ""
                            },
                            "default_value": "",
                            "tabs": "all",
                            "toolbar": "full",
                            "media_upload": 1,
                            "delay": 1
                        },
                        {
                            "key": "field_5eea94043af09",
                            "label": "Image",
                            "name": "image",
                            "type": "image",
                            "instructions": "",
                            "required": 0,
                            "conditional_logic": [
                                [
                                    {
                                        "field": "field_5eea93ac3af07",
                                        "operator": "==",
                                        "value": "image"
                                    }
                                ]
                            ],
                            "wrapper": {
                                "width": "",
                                "class": "",
                                "id": ""
                            },
                            "return_format": "array",
                            "preview_size": "medium",
                            "library": "all",
                            "min_width": "",
                            "min_height": "",
                            "min_size": "",
                            "max_width": "",
                            "max_height": "",
                            "max_size": "",
                            "mime_types": ""
                        }
                    ]
                }
            ]
        }
    ],
    "location": [
        [
            {
                "param": "block",
                "operator": "==",
                "value": "acf\/columns"
            }
        ]
    ],
    "menu_order": 0,
    "position": "normal",
    "style": "default",
    "label_placement": "top",
    "instruction_placement": "label",
    "hide_on_screen": "",
    "active": 1,
    "description": "",
    "modified": 1594319686
}